flu_geolocator/__init__.py
flu_geolocator/geolocator.py
flu_geolocator-0.0.1.dist-info/METADATA
flu_geolocator-0.0.1.dist-info/WHEEL
flu_geolocator-0.0.1.dist-info/top_level.txt
flu_geolocator-0.0.1.dist-info/RECORD
